Metadata-Version: 1.1
Name: qtrer
Version: 1.0.0
Summary: 对Qt翻译文件进行翻译的小工具
Home-page: https://github.com/xyz1001/PythonToolkit/tree/master/toolkit/QTranslatorHelper
Author: xyz1001
Author-email: zgzf1001@gmail.com
License: MIT
Keywords: python Qt translate
Platform: UNKNOWN
Classifier: Programming Language :: Python :: 3
